LICENSE.txt
MANIFEST.in
README.md
requirements.txt
setup.py
django_spreadsheetresponsemixin.egg-info/PKG-INFO
django_spreadsheetresponsemixin.egg-info/SOURCES.txt
django_spreadsheetresponsemixin.egg-info/dependency_links.txt
django_spreadsheetresponsemixin.egg-info/pbr.json
django_spreadsheetresponsemixin.egg-info/requires.txt
django_spreadsheetresponsemixin.egg-info/top_level.txt
spreadsheetresponsemixin/__init__.py
spreadsheetresponsemixin/views.py