Metadata-Version: 1.1
Name: django-spreadsheetresponsemixin
Version: 0.1.10
Summary: A mixin for views with a queryset that provides a CSV/Excel export.
Home-page: https://github.com/birdsarah/django-spreadsheetresponsemixin
Author: Sarah Bird
Author-email: sarah@bonvaya.com
License: GNU GENERAL PUBLIC LICENSE
